mobius_activations/__init__.py
mobius_activations/tensorflow.py
mobius_activations/torch.py
mobius_activations/visualize.py
mobius_activations-0.4.0.dist-info/licenses/LICENSE
mobius_activations-0.4.0.dist-info/METADATA
mobius_activations-0.4.0.dist-info/WHEEL
mobius_activations-0.4.0.dist-info/top_level.txt
mobius_activations-0.4.0.dist-info/RECORD
