Metadata-Version: 2.4
Name: mobius-activations
Version: 0.4.0
Summary: A  3D activation function for PyTorch and TensorFlow with geometric  properties.
Author-email: seabe kgodisho phala <phalakgodisho3@gmail.com>
Classifier: Programming Language :: Python :: 3
Classifier: License :: OSI Approved :: MIT License
Classifier: Operating System :: OS Independent
Classifier: Intended Audience :: Science/Research
Classifier: Topic :: Scientific/Engineering :: Artificial Intelligence
Requires-Python: >=3.8
License-File: LICENSE
Requires-Dist: numpy
Provides-Extra: torch
Requires-Dist: torch; extra == "torch"
Provides-Extra: tensorflow
Requires-Dist: tensorflow; extra == "tensorflow"
Provides-Extra: viz
Requires-Dist: matplotlib; extra == "viz"
Dynamic: license-file
